{
  "imports": [
    "_MSSymbolMaster.h"
  ],
  "classes": [
    "MSForeignSymbol",
    "NSArray",
    "NSSet"
  ],
  "protocol": false,
  "className": "MSSymbolMaster",
  "extends": "_MSSymbolMaster",
  "interfaces": [],
  "methods": {
    "copyPropertiesFrom:to:": {
      "name": "copyPropertiesFrom:to:",
      "bridgedName": "copyPropertiesFrom_to",
      "args": [
        {
          "type": "id"
        },
        {
          "type": "id"
        }
      ],
      "returns": "void",
      "kind": "class",
      "kindIndicator": "+"
    },
    "convertSymbolToArtboard:": {
      "name": "convertSymbolToArtboard:",
      "bridgedName": "convertSymbolToArtboard",
      "args": [
        {
          "type": "id"
        }
      ],
      "returns": "id",
      "kind": "class",
      "kindIndicator": "+"
    },
    "convertArtboardToSymbol:": {
      "name": "convertArtboardToSymbol:",
      "bridgedName": "convertArtboardToSymbol",
      "args": [
        {
          "type": "id"
        }
      ],
      "returns": "id",
      "kind": "class",
      "kindIndicator": "+"
    },
    ".cxx_destruct": {
      "name": ".cxx_destruct",
      "bridgedName": ".cxx_destruct",
      "args": [],
      "returns": "void",
      "kind": "instance",
      "kindIndicator": "-"
    },
    "limitsSelectionToBounds": {
      "name": "limitsSelectionToBounds",
      "bridgedName": "limitsSelectionToBounds",
      "args": [],
      "returns": "BOOL",
      "kind": "instance",
      "kindIndicator": "-"
    },
    "influencingSymbolIDsWithOverrides:": {
      "name": "influencingSymbolIDsWithOverrides:",
      "bridgedName": "influencingSymbolIDsWithOverrides",
      "args": [
        {
          "type": "id"
        }
      ],
      "returns": "id",
      "kind": "instance",
      "kindIndicator": "-"
    },
    "object:didChangeProperty:": {
      "name": "object:didChangeProperty:",
      "bridgedName": "object_didChangeProperty",
      "args": [
        {
          "type": "id"
        },
        {
          "type": "id"
        }
      ],
      "returns": "void",
      "kind": "instance",
      "kindIndicator": "-"
    },
    "notifySymbolInstancesOfChange": {
      "name": "notifySymbolInstancesOfChange",
      "bridgedName": "notifySymbolInstancesOfChange",
      "args": [],
      "returns": "void",
      "kind": "instance",
      "kindIndicator": "-"
    },
    "parentSymbol": {
      "name": "parentSymbol",
      "bridgedName": "parentSymbol",
      "args": [],
      "returns": "id",
      "kind": "instance",
      "kindIndicator": "-"
    },
    "rootForNameUniquing": {
      "name": "rootForNameUniquing",
      "bridgedName": "rootForNameUniquing",
      "args": [],
      "returns": "id",
      "kind": "instance",
      "kindIndicator": "-"
    },
    "ancestorIDsForLayerNamed:skip:": {
      "name": "ancestorIDsForLayerNamed:skip:",
      "bridgedName": "ancestorIDsForLayerNamed_skip",
      "args": [
        {
          "type": "id"
        },
        {
          "type": "id"
        }
      ],
      "returns": "id",
      "kind": "instance",
      "kindIndicator": "-"
    },
    "ancestorIDsForLayerNamed:": {
      "name": "ancestorIDsForLayerNamed:",
      "bridgedName": "ancestorIDsForLayerNamed",
      "args": [
        {
          "type": "id"
        }
      ],
      "returns": "id",
      "kind": "instance",
      "kindIndicator": "-"
    },
    "isSafeToDelete": {
      "name": "isSafeToDelete",
      "bridgedName": "isSafeToDelete",
      "args": [],
      "returns": "BOOL",
      "kind": "instance",
      "kindIndicator": "-"
    },
    "multiplyBy:": {
      "name": "multiplyBy:",
      "bridgedName": "multiplyBy",
      "args": [
        {
          "type": "double"
        }
      ],
      "returns": "void",
      "kind": "instance",
      "kindIndicator": "-"
    },
    "ungroup": {
      "name": "ungroup",
      "bridgedName": "ungroup",
      "args": [],
      "returns": "id",
      "kind": "instance",
      "kindIndicator": "-"
    },
    "removeFromParentAndDetachAllInstances": {
      "name": "removeFromParentAndDetachAllInstances",
      "bridgedName": "removeFromParentAndDetachAllInstances",
      "args": [],
      "returns": "void",
      "kind": "instance",
      "kindIndicator": "-"
    },
    "detachAllInstances": {
      "name": "detachAllInstances",
      "bridgedName": "detachAllInstances",
      "args": [],
      "returns": "void",
      "kind": "instance",
      "kindIndicator": "-"
    },
    "ensureSymbolIDUniqueInDocument:": {
      "name": "ensureSymbolIDUniqueInDocument:",
      "bridgedName": "ensureSymbolIDUniqueInDocument",
      "args": [
        {
          "type": "id"
        }
      ],
      "returns": "BOOL",
      "kind": "instance",
      "kindIndicator": "-"
    },
    "applyOverridesFromSource:": {
      "name": "applyOverridesFromSource:",
      "bridgedName": "applyOverridesFromSource",
      "args": [
        {
          "type": "id"
        }
      ],
      "returns": "void",
      "kind": "instance",
      "kindIndicator": "-"
    },
    "hasInstances": {
      "name": "hasInstances",
      "bridgedName": "hasInstances",
      "args": [],
      "returns": "BOOL",
      "kind": "instance",
      "kindIndicator": "-"
    },
    "nestedSymbolsSkipping:": {
      "name": "nestedSymbolsSkipping:",
      "bridgedName": "nestedSymbolsSkipping",
      "args": [
        {
          "type": "id"
        }
      ],
      "returns": "id",
      "kind": "instance",
      "kindIndicator": "-"
    },
    "influenceRectPaddingForInstances": {
      "name": "influenceRectPaddingForInstances",
      "bridgedName": "influenceRectPaddingForInstances",
      "args": [],
      "returns": "struct BCEdgePaddings",
      "kind": "instance",
      "kindIndicator": "-"
    },
    "newSymbolInstance": {
      "name": "newSymbolInstance",
      "bridgedName": "newSymbolInstance",
      "args": [],
      "returns": "id",
      "kind": "instance",
      "kindIndicator": "-"
    },
    "moveChildrenToIdenticalPositionAfterResizeFromRect:": {
      "name": "moveChildrenToIdenticalPositionAfterResizeFromRect:",
      "bridgedName": "moveChildrenToIdenticalPositionAfterResizeFromRect",
      "args": [
        {
          "type": "struct CGRect"
        }
      ],
      "returns": "void",
      "kind": "instance",
      "kindIndicator": "-"
    },
    "copyPropertiesToObject:options:": {
      "name": "copyPropertiesToObject:options:",
      "bridgedName": "copyPropertiesToObject_options",
      "args": [
        {
          "type": "id"
        },
        {
          "type": "unsigned long long"
        }
      ],
      "returns": "void",
      "kind": "instance",
      "kindIndicator": "-"
    },
    "syncPropertiesFromObject:": {
      "name": "syncPropertiesFromObject:",
      "bridgedName": "syncPropertiesFromObject",
      "args": [
        {
          "type": "id"
        }
      ],
      "returns": "void",
      "kind": "instance",
      "kindIndicator": "-"
    },
    "performInitWithImmutableModelObject:": {
      "name": "performInitWithImmutableModelObject:",
      "bridgedName": "performInitWithImmutableModelObject",
      "args": [
        {
          "type": "id"
        }
      ],
      "returns": "void",
      "kind": "instance",
      "kindIndicator": "-"
    },
    "initWithFrame:": {
      "name": "initWithFrame:",
      "bridgedName": "initWithFrame",
      "args": [
        {
          "type": "struct CGRect"
        }
      ],
      "returns": "id",
      "kind": "instance",
      "kindIndicator": "-"
    },
    "hasSliceIcon": {
      "name": "hasSliceIcon",
      "bridgedName": "hasSliceIcon",
      "args": [],
      "returns": "BOOL",
      "kind": "instance",
      "kindIndicator": "-"
    },
    "unselectedPreviewImage": {
      "name": "unselectedPreviewImage",
      "bridgedName": "unselectedPreviewImage",
      "args": [],
      "returns": "id",
      "kind": "instance",
      "kindIndicator": "-"
    },
    "selectedPreviewImage": {
      "name": "selectedPreviewImage",
      "bridgedName": "selectedPreviewImage",
      "args": [],
      "returns": "id",
      "kind": "instance",
      "kindIndicator": "-"
    },
    "optimalBoundingBox": {
      "name": "optimalBoundingBox",
      "bridgedName": "optimalBoundingBox",
      "args": [],
      "returns": "struct CGRect",
      "kind": "instance",
      "kindIndicator": "-"
    },
    "canSnapSizeToLayer:": {
      "name": "canSnapSizeToLayer:",
      "bridgedName": "canSnapSizeToLayer",
      "args": [
        {
          "type": "id"
        }
      ],
      "returns": "BOOL",
      "kind": "instance",
      "kindIndicator": "-"
    },
    "canSnapToLayer:": {
      "name": "canSnapToLayer:",
      "bridgedName": "canSnapToLayer",
      "args": [
        {
          "type": "id"
        }
      ],
      "returns": "BOOL",
      "kind": "instance",
      "kindIndicator": "-"
    }
  },
  "properties": {
    "changeIdentifier": {
      "name": "changeIdentifier",
      "pointer": false,
      "type": "long long",
      "attributes": [
        "nonatomic"
      ]
    },
    "allInfluencedInstances": {
      "name": "allInfluencedInstances",
      "pointer": true,
      "type": "NSArray",
      "attributes": [
        "readonly",
        "nonatomic"
      ]
    },
    "nestedSymbols": {
      "name": "nestedSymbols",
      "pointer": true,
      "type": "NSSet",
      "attributes": [
        "readonly",
        "nonatomic"
      ]
    },
    "allInstances": {
      "name": "allInstances",
      "pointer": true,
      "type": "NSArray",
      "attributes": [
        "readonly",
        "nonatomic"
      ]
    },
    "isForeign": {
      "name": "isForeign",
      "pointer": false,
      "type": "BOOL",
      "attributes": [
        "readonly",
        "nonatomic"
      ]
    },
    "foreignSymbol": {
      "name": "foreignSymbol",
      "pointer": true,
      "type": "MSForeignSymbol",
      "attributes": [
        "readonly",
        "nonatomic"
      ]
    }
  }
}