{
  "imports": [
    "NSObject.h"
  ],
  "classes": [
    "NSSliderAccessory"
  ],
  "protocol": true,
  "className": "NSSliderAccessoryContainer",
  "interfaces": [],
  "methods": {
    "_incrementValue:": {
      "name": "_incrementValue:",
      "bridgedName": "_incrementValue",
      "args": [
        {
          "name": "_incrementValue",
          "type": "BOOL"
        }
      ],
      "returns": "void",
      "kind": "instance",
      "kindIndicator": "-"
    },
    "sendAction": {
      "name": "sendAction",
      "bridgedName": "sendAction",
      "args": [],
      "returns": "void",
      "kind": "instance",
      "kindIndicator": "-"
    }
  },
  "properties": {
    "_hasStepBehaviorContext": {
      "name": "_hasStepBehaviorContext",
      "pointer": false,
      "type": "BOOL",
      "attributes": [
        "readonly"
      ]
    },
    "maximumValueAccessory": {
      "name": "maximumValueAccessory",
      "pointer": true,
      "type": "NSSliderAccessory",
      "attributes": [
        "readonly"
      ]
    },
    "minimumValueAccessory": {
      "name": "minimumValueAccessory",
      "pointer": true,
      "type": "NSSliderAccessory",
      "attributes": [
        "readonly"
      ]
    }
  }
}