{
  "imports": [],
  "classes": [
    "MSLocalDataSupplier"
  ],
  "protocol": true,
  "className": "MSLocalDataSupplierDelegate",
  "interfaces": [],
  "methods": {
    "locaDataSupplierDataChanged:": {
      "name": "locaDataSupplierDataChanged:",
      "bridgedName": "locaDataSupplierDataChanged",
      "args": [
        {
          "name": "locaDataSupplierDataChanged",
          "type": "MSLocalDataSupplier *"
        }
      ],
      "returns": "void",
      "kind": "instance",
      "kindIndicator": "-"
    }
  },
  "properties": {}
}