{
  "imports": [
    "NSObject.h"
  ],
  "classes": [
    "NSMutableArray"
  ],
  "protocol": false,
  "className": "MSPasteboardManager",
  "extends": "NSObject",
  "interfaces": [],
  "methods": {
    "registerViewForSupportedDraggedTypes:": {
      "name": "registerViewForSupportedDraggedTypes:",
      "bridgedName": "registerViewForSupportedDraggedTypes",
      "args": [
        {
          "type": "id"
        }
      ],
      "returns": "void",
      "kind": "instance",
      "kindIndicator": "-"
    },
    "registerWriter:": {
      "name": "registerWriter:",
      "bridgedName": "registerWriter",
      "args": [
        {
          "type": "id"
        }
      ],
      "returns": "void",
      "kind": "instance",
      "kindIndicator": "-"
    },
    "registerReader:": {
      "name": "registerReader:",
      "bridgedName": "registerReader",
      "args": [
        {
          "type": "id"
        }
      ],
      "returns": "void",
      "kind": "instance",
      "kindIndicator": "-"
    },
    "writePasteboardLayers:toPasteboard:": {
      "name": "writePasteboardLayers:toPasteboard:",
      "bridgedName": "writePasteboardLayers_toPasteboard",
      "args": [
        {
          "type": "id"
        },
        {
          "type": "id"
        }
      ],
      "returns": "void",
      "kind": "instance",
      "kindIndicator": "-"
    },
    "readPasteboardLayersFromDrag:": {
      "name": "readPasteboardLayersFromDrag:",
      "bridgedName": "readPasteboardLayersFromDrag",
      "args": [
        {
          "type": "id"
        }
      ],
      "returns": "id",
      "kind": "instance",
      "kindIndicator": "-"
    },
    "readPasteboardLayersFromPasteboard:options:": {
      "name": "readPasteboardLayersFromPasteboard:options:",
      "bridgedName": "readPasteboardLayersFromPasteboard_options",
      "args": [
        {
          "type": "id"
        },
        {
          "type": "unsigned long long"
        }
      ],
      "returns": "id",
      "kind": "instance",
      "kindIndicator": "-"
    },
    "applicationPasteboardManager": {
      "name": "applicationPasteboardManager",
      "bridgedName": "applicationPasteboardManager",
      "args": [],
      "returns": "id",
      "kind": "class",
      "kindIndicator": "+"
    },
    ".cxx_destruct": {
      "name": ".cxx_destruct",
      "bridgedName": ".cxx_destruct",
      "args": [],
      "returns": "void",
      "kind": "instance",
      "kindIndicator": "-"
    },
    "readPasteboardLayersFromPasteboard:options:sender:": {
      "name": "readPasteboardLayersFromPasteboard:options:sender:",
      "bridgedName": "readPasteboardLayersFromPasteboard_options_sender",
      "args": [
        {
          "type": "id"
        },
        {
          "type": "unsigned long long"
        },
        {
          "type": "id"
        }
      ],
      "returns": "id",
      "kind": "instance",
      "kindIndicator": "-"
    },
    "init": {
      "name": "init",
      "bridgedName": "init",
      "args": [],
      "returns": "id",
      "kind": "instance",
      "kindIndicator": "-"
    },
    "registerDefaultReadersAndWriters": {
      "name": "registerDefaultReadersAndWriters",
      "bridgedName": "registerDefaultReadersAndWriters",
      "args": [],
      "returns": "void",
      "kind": "instance",
      "kindIndicator": "-"
    }
  },
  "properties": {
    "writers": {
      "name": "writers",
      "pointer": true,
      "type": "NSMutableArray",
      "attributes": [
        "retain",
        "nonatomic"
      ]
    },
    "readers": {
      "name": "readers",
      "pointer": true,
      "type": "NSMutableArray",
      "attributes": [
        "retain",
        "nonatomic"
      ]
    }
  }
}