{
  "imports": [],
  "classes": [
    "NSColor"
  ],
  "protocol": false,
  "className": "_NSScrubberRoundedBackgroundSelectionStyle",
  "extends": "NSScrubberSelectionStyle",
  "interfaces": [],
  "methods": {
    "makeSelectionView": {
      "name": "makeSelectionView",
      "bridgedName": "makeSelectionView",
      "args": [],
      "returns": "id",
      "kind": "instance",
      "kindIndicator": "-"
    },
    "dealloc": {
      "name": "dealloc",
      "bridgedName": "dealloc",
      "args": [],
      "returns": "void",
      "kind": "instance",
      "kindIndicator": "-"
    },
    "encodeWithCoder:": {
      "name": "encodeWithCoder:",
      "bridgedName": "encodeWithCoder",
      "args": [
        {
          "type": "id"
        }
      ],
      "returns": "void",
      "kind": "instance",
      "kindIndicator": "-"
    },
    "initWithCoder:": {
      "name": "initWithCoder:",
      "bridgedName": "initWithCoder",
      "args": [
        {
          "type": "id"
        }
      ],
      "returns": "id",
      "kind": "instance",
      "kindIndicator": "-"
    }
  },
  "properties": {
    "tintColor": {
      "name": "tintColor",
      "pointer": true,
      "type": "NSColor",
      "attributes": [
        "copy"
      ]
    }
  }
}