{
  "imports": [
    "_MSSymbolContainer.h"
  ],
  "classes": [],
  "protocol": false,
  "className": "MSSymbolContainer",
  "extends": "_MSSymbolContainer",
  "interfaces": [],
  "methods": {
    "enumeratePotentialInstancesInContainer:block:": {
      "name": "enumeratePotentialInstancesInContainer:block:",
      "bridgedName": "enumeratePotentialInstancesInContainer_block",
      "args": [
        {
          "name": "enumeratePotentialInstancesInContainer",
          "type": "id"
        },
        {
          "name": "block",
          "type": "CDUnknownBlockType"
        }
      ],
      "returns": "void",
      "kind": "instance",
      "kindIndicator": "-"
    }
  },
  "properties": {}
}